setup.py
bin/wpupdate.py
wpupdater/WPBlog.py
wpupdater/__init__.py
wpupdater/utils.py
wpupdater.egg-info/PKG-INFO
wpupdater.egg-info/SOURCES.txt
wpupdater.egg-info/dependency_links.txt
wpupdater.egg-info/requires.txt
wpupdater.egg-info/top_level.txt