Metadata-Version: 1.1
Name: wpupdater
Version: 0.1-f1
Summary: WordPress Updater
Home-page: http://github.com/infakt/wpupdater
Author: Marcin Matlaszek <emate>, inFakt DevTeam
Author-email: mmatlaszek@gmail.com, marcin.matlaszek@infakt.pl, devteam@infakt.pl
License: UNKNOWN
Download-URL: http://github.com/infakt/wpupdater
Platform: UNKNOWN
